[{"status": 0, "message": "ok", "results": [{"name": "苏州", "location": {"lat": 31.303565, "lng": 120.592412}, "uid": "40ca934b3252e3a58a36eee7"}]}, {"status": 0, "message": "ok", "results": [{"name": "湖州", "location": {"lat": 30.898964, "lng": 120.094518}, "uid": "7dde50f510b5a7a5118824e7"}]}, {"status": 0, "message": "ok", "results": [{"name": "灵宝", "location": {"lat": 34.523144, "lng": 110.900406}, "uid": "62e42a2ffe531d422811d1eb"}]}, {"status": 0, "message": "ok", "results": [{"name": "西安", "location": {"lat": 34.347269, "lng": 108.946465}, "uid": "6004101013367be6b817e7e7"}]}]