[{"status": 0, "message": "ok", "results": [{"name": "绍兴", "location": {"lat": 30.03637, "lng": 120.585477}, "uid": "1205212d15f096fb9fec2be7"}]}, {"status": 0, "message": "ok", "results": [{"name": "西安", "location": {"lat": 34.347269, "lng": 108.946465}, "uid": "6004101013367be6b817e7e7"}]}, {"status": 0, "message": "ok", "results": [{"name": "洛阳", "location": {"lat": 34.624264, "lng": 112.459424}, "uid": "3e23636a35284eacd618b7e7"}]}, {"status": 0, "message": "ok", "results": [{"name": "襄阳", "location": {"lat": 32.014797, "lng": 112.128533}, "uid": "514a79d8cd6e54eaaaf0cd0d"}]}, {"status": 0, "message": "ok", "results": [{"name": "南京", "location": {"lat": 32.064652, "lng": 118.802422}, "uid": "73d80fbb9cf7cc6a1d1d11e7"}]}, {"status": 0, "message": "ok", "results": [{"name": "扬州", "location": {"lat": 32.400676, "lng": 119.419423}, "uid": "9e133d19c0cfce470f0a70e7"}]}, {"status": 0, "message": "ok", "results": [{"name": "汝南", "location": {"lat": 33.013141, "lng": 114.36941}, "uid": "7a396597f02890440869d9eb"}]}]