[{"status": 0, "message": "ok", "results": [{"name": "大名", "location": {"lat": 36.291288, "lng": 115.15461}, "uid": "2abada39d64eb41cdbecedeb"}]}, {"status": 0, "message": "ok", "results": [{"name": "华阴", "location": {"lat": 34.571801, "lng": 110.098605}, "uid": "59143023ffd171b4e50738e9"}]}, {"status": 0, "message": "ok", "results": [{"name": "大名", "location": {"lat": 36.291288, "lng": 115.15461}, "uid": "2abada39d64eb41cdbecedeb"}]}, {"status": 0, "message": "ok", "results": [{"name": "开封", "location": {"lat": 34.802885, "lng": 114.314595}, "uid": "a71bc211e1d36cf6ee74f8e7"}]}, {"status": 0, "message": "ok", "results": [{"name": "渭南", "location": {"lat": 34.505715, "lng": 109.516593}, "uid": "e4f715e686e315b325e0a0e7"}]}, {"status": 0, "message": "ok", "results": [{"name": "秭归", "location": {"lat": 30.831931, "lng": 110.984451}, "uid": "0a173c297f7aa865f6c59ce9"}]}, {"status": 0, "message": "ok", "results": [{"name": "巴东", "location": {"lat": 31.047994, "lng": 110.347325}, "uid": "3cbd8a5c0f3bd0acf02d83e8"}]}, {"status": 0, "message": "ok", "results": [{"name": "宜昌", "location": {"lat": 30.697446, "lng": 111.292552}, "uid": "cda0ba05ba85655ecae33ce7"}]}, {"status": 0, "message": "ok", "results": [{"name": "成安", "location": {"lat": 36.449798, "lng": 114.676576}, "uid": "40ce934b3252e3a58a36eeeb"}]}, {"status": 0, "message": "ok", "results": [{"name": "陕西", "location": {"lat": 34.275807, "lng": 108.960389}, "uid": "89d9491c4c1e9a9b3ce231e6"}]}, {"status": 0, "message": "ok", "results": [{"name": "东平", "location": {"lat": 35.941908, "lng": 116.477598}, "uid": "52fe61027b19e457eaf853ec"}]}, {"status": 0, "message": "ok", "results": [{"name": "开封", "location": {"lat": 34.802885, "lng": 114.314595}, "uid": "a71bc211e1d36cf6ee74f8e7"}]}, {"status": 0, "message": "ok", "results": [{"name": "青州", "location": {"lat": 36.690417, "lng": 118.486533}, "uid": "8abd4e4d09219f8eae0457ee"}]}, {"status": 0, "message": "ok", "results": [{"name": "开封", "location": {"lat": 34.802885, "lng": 114.314595}, "uid": "a71bc211e1d36cf6ee74f8e7"}]}, {"status": 0, "message": "ok", "results": [{"name": "邓州", "location": {"lat": 32.693918, "lng": 112.093418}, "uid": "91d88de7681fc6473904b1e9"}]}, {"status": 0, "message": "ok", "results": [{"name": "孟州", "location": {"lat": 34.913598, "lng": 112.797393}, "uid": "d0f3cf38bc8eb39235b06cef"}]}, {"status": 0, "message": "ok", "results": [{"name": "大荔", "location": {"lat": 34.801833, "lng": 109.948453}, "uid": "672503f21eab69ac1b94c6ec"}]}, {"status": 0, "message": "ok", "results": [{"name": "凤翔", "location": {"lat": 34.527616, "lng": 107.40738}, "uid": "4a41842be5f1bd4cf603b8ec"}]}, {"status": 0, "message": "ok", "results": [{"name": "南部", "location": {"lat": 31.353705, "lng": 106.043582}, "uid": "e9d13a7f2e2bce8cab059dec"}]}, {"status": 0, "message": "ok", "results": [{"name": "南京", "location": {"lat": 32.064652, "lng": 118.802422}, "uid": "73d80fbb9cf7cc6a1d1d11e7"}]}, {"status": 0, "message": "ok", "results": [{"name": "凤翔", "location": {"lat": 34.527616, "lng": 107.40738}, "uid": "4a41842be5f1bd4cf603b8ec"}]}, {"status": 0, "message": "ok", "results": [{"name": "开封", "location": {"lat": 34.802885, "lng": 114.314595}, "uid": "a71bc211e1d36cf6ee74f8e7"}]}, {"status": 0, "message": "ok", "results": [{"name": "滑县", "location": {"lat": 35.581044, "lng": 114.525553}, "uid": "b2557f17034f2e3f59bbbce9"}]}, {"status": 0, "message": "ok", "results": [{"name": "濮阳", "location": {"lat": 35.767593, "lng": 115.035593}, "uid": "a0dc0fe88714679d54bfffe7"}]}, {"status": 0, "message": "ok", "results": [{"name": "开封", "location": {"lat": 34.802885, "lng": 114.314595}, "uid": "a71bc211e1d36cf6ee74f8e7"}]}, {"status": 0, "message": "ok", "results": [{"name": "三门峡", "location": {"lat": 34.778326, "lng": 111.20653}, "uid": "0a25afbd5073da5ceb56fae7"}]}, {"status": 0, "message": "ok", "results": [{"name": "洛阳", "location": {"lat": 34.624264, "lng": 112.459424}, "uid": "3e23636a35284eacd618b7e7"}]}, {"status": 0, "message": "ok", "results": [{"name": "开封", "location": {"lat": 34.802885, "lng": 114.314595}, "uid": "a71bc211e1d36cf6ee74f8e7"}]}, {"status": 0, "message": "ok", "results": [{"name": "三门峡", "location": {"lat": 34.778326, "lng": 111.20653}, "uid": "0a25afbd5073da5ceb56fae7"}]}, {"status": 0, "message": "ok", "results": [{"name": "曲阜", "location": {"lat": 35.587374, "lng": 116.993414}, "uid": "484581b735f607d3cafa5fee"}]}, {"status": 0, "message": "ok", "results": [{"name": "三门峡", "location": {"lat": 34.778326, "lng": 111.20653}, "uid": "0a25afbd5073da5ceb56fae7"}]}, {"status": 0, "message": "ok", "results": [{"name": "大名", "location": {"lat": 36.291288, "lng": 115.15461}, "uid": "2abada39d64eb41cdbecedeb"}]}, {"status": 0, "message": "ok", "results": [{"name": "开封", "location": {"lat": 34.802885, "lng": 114.314595}, "uid": "a71bc211e1d36cf6ee74f8e7"}]}, {"status": 0, "message": "ok", "results": [{"name": "洛阳", "location": {"lat": 34.624264, "lng": 112.459424}, "uid": "3e23636a35284eacd618b7e7"}]}]