[{"status": 0, "message": "ok", "results": [{"name": "埇桥", "location": {"lat": 33.646131, "lng": 116.983479}, "uid": "d42db2ff5b009d930ab93aed"}]}, {"status": 0, "message": "ok", "results": [{"name": "亳州", "location": {"lat": 33.850642, "lng": 115.784466}, "uid": "4606101ca8a6e39140e192e7"}]}, {"status": 0, "message": "ok", "results": [{"name": "富阳", "location": {"lat": 30.054723, "lng": 119.966554}, "uid": "284eff2b94fb88054bcc4aef"}]}, {"status": 0, "message": "ok", "results": [{"name": "杭州", "location": {"lat": 30.253082, "lng": 120.21551}, "uid": "99f429f6963d1f271fe999e7"}]}, {"status": 0, "message": "ok", "results": [{"name": "天台", "location": {"lat": 29.149515, "lng": 121.013556}, "uid": "c41dc3e693fd1da9c72ba1ef"}]}, {"status": 0, "message": "ok", "results": [{"name": "新昌", "location": {"lat": 29.50554, "lng": 120.910574}, "uid": "62e305a521f094a72ce67be9"}]}, {"status": 0, "message": "ok", "results": [{"name": "绍兴", "location": {"lat": 30.03637, "lng": 120.585477}, "uid": "1205212d15f096fb9fec2be7"}]}, {"status": 0, "message": "ok", "results": [{"name": "乐清", "location": {"lat": 28.11818, "lng": 120.9925}, "uid": "2913bba98d112471ca1b95ec"}]}, {"status": 0, "message": "ok", "results": [{"name": "温州", "location": {"lat": 28.001086, "lng": 120.706479}, "uid": "c53450076cf31073276e98e7"}]}, {"status": 0, "message": "ok", "results": [{"name": "京山", "location": {"lat": 31.024331, "lng": 113.12655}, "uid": "4604a2382e18d696f8f0cbeb"}]}, {"status": 0, "message": "ok", "results": [{"name": "襄阳", "location": {"lat": 32.014797, "lng": 112.128533}, "uid": "514a79d8cd6e54eaaaf0cd0d"}]}]