[{"status": 0, "message": "ok", "results": [{"name": "济宁", "location": {"lat": 35.420177, "lng": 116.593614}, "uid": "3d23c7e0f91d160e6cc02ce7"}]}, {"status": 0, "message": "ok", "results": [{"name": "单县", "location": {"lat": 34.784658, "lng": 116.111584}, "uid": "c4e66680b6f2d35bad31e5ed"}]}, {"status": 0, "message": "ok", "results": [{"name": "兖州", "location": {"lat": 35.557953, "lng": 116.790119}, "uid": "6e891cf468b039602bfc484e"}]}, {"status": 0, "message": "ok", "results": [{"name": "商丘", "location": {"lat": 34.420202, "lng": 115.662449}, "uid": "8399702dc8e2ee51fe0eb0e7"}]}, {"status": 0, "message": "ok", "results": [{"name": "扬州", "location": {"lat": 32.400676, "lng": 119.419423}, "uid": "9e133d19c0cfce470f0a70e7"}]}, {"status": 0, "message": "ok", "results": [{"name": "镇江", "location": {"lat": 32.194717, "lng": 119.43049}, "uid": "dbb3f15e7d51c145364aaee7"}]}, {"status": 0, "message": "ok", "results": [{"name": "南京", "location": {"lat": 32.064652, "lng": 118.802422}, "uid": "73d80fbb9cf7cc6a1d1d11e7"}]}]